certmailer/__init__.py
certmailer/cli.py
certmailer/cli_config.py
certmailer/cli_edit_run.py
certmailer/cli_jobs.py
certmailer/eventoL_import.py
certmailer/gen_mail.py
certmailer/gen_pdf.py
certmailer/jobs.py
certmailer/make_template.py
certmailer/receivers.py
certmailer/template.zip
certmailer/utils.py
certmailer-2.0.0.data/scripts/certmail.py
certmailer-2.0.0.dist-info/LICENSE
certmailer-2.0.0.dist-info/METADATA
certmailer-2.0.0.dist-info/WHEEL
certmailer-2.0.0.dist-info/entry_points.txt
certmailer-2.0.0.dist-info/top_level.txt
certmailer-2.0.0.dist-info/RECORD
