Metadata-Version: 2.1
Name: certmailer
Version: 2.0.0
Summary: To download, create and mail certificate on events
Home-page: https://github.com/marian-vignau/certmailer
Author: María Andrea Vignau
Author-email: mavignau@gmail.com
License: UNKNOWN
Platform: UNKNOWN
Classifier: Programming Language :: Python :: 3
Classifier: Operating System :: OS Independent
Classifier: Development Status :: 5 - Production/Stable
Classifier: Environment :: Console
Classifier: Intended Audience :: Information Technology
Classifier: License :: OSI Approved :: GNU General Public License v3 (GPLv3)
Classifier: Natural Language :: English
Classifier: Programming Language :: Python :: 3
Classifier: Topic :: Communications :: Email
Requires-Python: >=3.6
Requires-Dist: PyYaml
Requires-Dist: mailjet-rest
Requires-Dist: appdirs
Requires-Dist: click
